django_kongoauth-0.1.dist-info/DESCRIPTION.rst
django_kongoauth-0.1.dist-info/METADATA
django_kongoauth-0.1.dist-info/RECORD
django_kongoauth-0.1.dist-info/WHEEL
django_kongoauth-0.1.dist-info/metadata.json
django_kongoauth-0.1.dist-info/top_level.txt
tests/__init__.py
tests/test_authentication.py
tests/test_user.py
tests/testutils.py
